[{"nom":"Hooks","prenom":"Angular","email":"angularhooks0@key.com","site":"4"},{"nom":"Hooks","prenom":"Angular","email":"angularhooks1@key.com","site":"4"},{"nom":"Hooks","prenom":"Angular","email":"angularhooks2@key.com","site":"4"},{"nom":"Hooks","prenom":"Angular","email":"angularhooks3@key.com","site":"4"},{"nom":"Hooks","prenom":"Angular","email":"angularhooks4@key.com","site":"4"},{"nom":"Hooks","prenom":"Angular","email":"angularhooks5@key.com","site":"4"},{"nom":"Hooks","prenom":"Angular","email":"angularhooks6@key.com","site":"4"},{"nom":"Hooks","prenom":"Angular","email":"angularhooks7@key.com","site":"4"},{"nom":"Hooks","prenom":"Angular","email":"angularhooks8@key.com","site":"4"},{"nom":"Hooks","prenom":"Angular","email":"angularhooks9@key.com","site":"4"}]